nk/__init__.py
nk/nk.mp4
nk/nkrean.py
nkrean-1.0.0.dist-info/METADATA
nkrean-1.0.0.dist-info/WHEEL
nkrean-1.0.0.dist-info/top_level.txt
nkrean-1.0.0.dist-info/RECORD
