Metadata-Version: 2.4
Name: nkrean
Version: 1.0.0
Requires-Dist: opencv-python
Dynamic: requires-dist
